cellcube_handset_simulator/__init__.py
cellcube_handset_simulator/__main__.py
cellcube_handset_simulator/server.py
cellcube_handset_simulator/static/.DS_Store
cellcube_handset_simulator/static/assets/.DS_Store
cellcube_handset_simulator/static/assets/img/.DS_Store
cellcube_handset_simulator/static/assets/img/favicons/.DS_Store
cellcube_handset_simulator/static/assets/img/favicons/apple-touch-icon.png
cellcube_handset_simulator/static/assets/img/favicons/favicon-16x16.png
cellcube_handset_simulator/static/assets/img/favicons/favicon-32x32.png
cellcube_handset_simulator/static/assets/img/favicons/favicon.ico
cellcube_handset_simulator/static/assets/img/favicons/manifest.json
cellcube_handset_simulator/static/assets/img/favicons/safari-pinned-tab.svg
cellcube_handset_simulator/static/boosted/css/boosted-grid.css
cellcube_handset_simulator/static/boosted/css/boosted-grid.css.map
cellcube_handset_simulator/static/boosted/css/boosted-grid.min.css
cellcube_handset_simulator/static/boosted/css/boosted-grid.min.css.map
cellcube_handset_simulator/static/boosted/css/boosted-grid.rtl.css
cellcube_handset_simulator/static/boosted/css/boosted-grid.rtl.css.map
cellcube_handset_simulator/static/boosted/css/boosted-grid.rtl.min.css
cellcube_handset_simulator/static/boosted/css/boosted-grid.rtl.min.css.map
cellcube_handset_simulator/static/boosted/css/boosted-reboot.css
cellcube_handset_simulator/static/boosted/css/boosted-reboot.css.map
cellcube_handset_simulator/static/boosted/css/boosted-reboot.min.css
cellcube_handset_simulator/static/boosted/css/boosted-reboot.min.css.map
cellcube_handset_simulator/static/boosted/css/boosted-reboot.rtl.css
cellcube_handset_simulator/static/boosted/css/boosted-reboot.rtl.css.map
cellcube_handset_simulator/static/boosted/css/boosted-reboot.rtl.min.css
cellcube_handset_simulator/static/boosted/css/boosted-reboot.rtl.min.css.map
cellcube_handset_simulator/static/boosted/css/boosted-utilities.css
cellcube_handset_simulator-0.2.6.dist-info/LICENSE
cellcube_handset_simulator-0.2.6.dist-info/METADATA
cellcube_handset_simulator-0.2.6.dist-info/WHEEL
cellcube_handset_simulator-0.2.6.dist-info/top_level.txt
cellcube_handset_simulator-0.2.6.dist-info/RECORD
