Metadata-Version: 2.1
Name: cellcube-handset-simulator
Version: 0.2.6
Summary: A Python library for simulating handset
Home-page: https://github.com/fjamon/python-cellcube-handset-simulator
Author: François Joseph AMON D''ABY
Author-email: ange_amon@live.fr
License: UNKNOWN
Project-URL: Bug Tracker, https://github.com/fjamon/python-cellcube-handset-simulator/issues
Platform: UNKNOWN
Classifier: Programming Language :: Python :: 3
Classifier: License :: OSI Approved :: MIT License
Classifier: Operating System :: OS Independent
Requires-Python: >=3.6
License-File: LICENSE
Requires-Dist: flask
Requires-Dist: requests
Requires-Dist: cellcube-xml-page-builder (>=0.2.4)
